psd2/__init__.py
psd2/psd2.py
psd2-0.0.4.dist-info/LICENSE
psd2-0.0.4.dist-info/METADATA
psd2-0.0.4.dist-info/WHEEL
psd2-0.0.4.dist-info/top_level.txt
psd2-0.0.4.dist-info/RECORD
