Metadata-Version: 2.1
Name: psd2
Version: 0.0.4
Summary: Estimate power spectral density characteristics using Welch's method
Home-page: https://github.com/demotu/psd2
Author: Marcos Duarte
Author-email: duartexyz@gmail.com
License: UNKNOWN
Platform: UNKNOWN
Classifier: Programming Language :: Python :: 3
Classifier: License :: OSI Approved :: MIT License
Classifier: Operating System :: OS Independent
Requires-Python: >=3.6
